google_auth_decoder/__init__.py
google_auth_decoder/cli.py
google_auth_decoder/decoder.py
google_auth_decoder/google_auth.proto
google_auth_decoder/google_auth_pb2.py
google_auth_decoder/items.py
google_auth_decoder/py.typed
google_auth_decoder/tests/__init__.py
google_auth_decoder/tests/test_decoder.py
google_auth_decoder-0.3.0.dist-info/METADATA
google_auth_decoder-0.3.0.dist-info/WHEEL
google_auth_decoder-0.3.0.dist-info/entry_points.txt
google_auth_decoder-0.3.0.dist-info/licenses/LICENSE
google_auth_decoder-0.3.0.dist-info/RECORD
