Metadata-Version: 2.4
Name: google-auth-decoder
Version: 0.3.0
Summary: Add your description here
Project-URL: Repository, https://github.com/elisey/google_auth_decoder
Author-email: Elisei <elisey.rav@gmail.com>
License-File: LICENSE
Requires-Python: >=3.13
Requires-Dist: protobuf==5.29.3
